embloy_sdk/__init__.py
embloy_sdk/embloy_client.py
embloy_sdk/embloy_session.py
tests/__init__.py
tests/test_embloy_client.py
embloy_sdk-0.3.28.dist-info/LICENSE
embloy_sdk-0.3.28.dist-info/METADATA
embloy_sdk-0.3.28.dist-info/WHEEL
embloy_sdk-0.3.28.dist-info/top_level.txt
embloy_sdk-0.3.28.dist-info/RECORD
