Metadata-Version: 2.1
Name: embloy_sdk
Version: 0.3.28
Summary: Embloy's SDK for Python
Home-page: https://github.com/embloy/embloy-python
Author: Carlo Bortolan
Author-email: carlobortolan@gmail.com
Classifier: Programming Language :: Python :: 3
Classifier: License :: OSI Approved :: GNU Affero General Public License v3
Classifier: Operating System :: OS Independent
License-File: LICENSE
Requires-Dist: requests
